cosmocloud/__init__.py
cosmocloud/main.py
cosmocloud-0.0.6.dist-info/licenses/LICENSE
cosmocloud-0.0.6.dist-info/METADATA
cosmocloud-0.0.6.dist-info/WHEEL
cosmocloud-0.0.6.dist-info/entry_points.txt
cosmocloud-0.0.6.dist-info/top_level.txt
cosmocloud-0.0.6.dist-info/RECORD
